dm_pix/__init__.py
dm_pix/py.typed
dm_pix/_src/__init__.py
dm_pix/_src/api_test.py
dm_pix/_src/augment.py
dm_pix/_src/augment_test.py
dm_pix/_src/color_conversion.py
dm_pix/_src/color_conversion_test.py
dm_pix/_src/depth_and_space.py
dm_pix/_src/depth_and_space_test.py
dm_pix/_src/interpolation.py
dm_pix/_src/interpolation_test.py
dm_pix/_src/metrics.py
dm_pix/_src/metrics_test.py
dm_pix/_src/patch.py
dm_pix/_src/patch_test.py
dm_pix/_src/test_utils.py
dm_pix/images/pix_logo.png
dm_pix-0.4.3.dist-info/LICENSE
dm_pix-0.4.3.dist-info/WHEEL
dm_pix-0.4.3.dist-info/METADATA
dm_pix-0.4.3.dist-info/RECORD
