Metadata-Version: 2.1
Name: dm_pix
Version: 0.4.3
Summary: PIX is an image processing library in JAX, for JAX.
Author-email: Google DeepMind <pix-dev@google.com>
Requires-Python: >=3.8
Classifier: Development Status :: 4 - Beta
Classifier: Intended Audience :: Developers
Classifier: Intended Audience :: Education
Classifier: Intended Audience :: Science/Research
Classifier: License :: OSI Approved :: Apache Software License
Classifier: Programming Language :: Python
Classifier: Programming Language :: Python :: 3
Classifier: Topic :: Scientific/Engineering :: Artificial Intelligence
Classifier: Topic :: Scientific/Engineering :: Image Processing
Classifier: Topic :: Scientific/Engineering :: Mathematics
Classifier: Topic :: Software Development :: Libraries
Classifier: Topic :: Software Development :: Libraries :: Python Modules
Requires-Dist: chex>=0.0.6
Requires-Dist: sphinx>=6.0.0 ; extra == "docs"
Requires-Dist: sphinx_rtd_theme ; extra == "docs"
Requires-Dist: sphinxcontrib-katex ; extra == "docs"
Requires-Dist: sphinxcontrib-bibtex ; extra == "docs"
Requires-Dist: sphinx-autodoc-typehints ; extra == "docs"
Requires-Dist: IPython ; extra == "docs"
Requires-Dist: ipykernel ; extra == "docs"
Requires-Dist: pandoc ; extra == "docs"
Requires-Dist: myst_nb ; extra == "docs"
Requires-Dist: docutils ; extra == "docs"
Requires-Dist: matplotlib ; extra == "docs"
Requires-Dist: Pillow ; extra == "examples"
Requires-Dist: jax>=0.2.17 ; extra == "extras"
Requires-Dist: jaxlib>=0.1.69 ; extra == "extras"
Requires-Dist: scipy ; extra == "test"
Requires-Dist: tensorflow ; extra == "test"
Requires-Dist: pytest-xdist ; extra == "test"
Provides-Extra: docs
Provides-Extra: examples
Provides-Extra: extras
Provides-Extra: test
